.gitignore
LICENSE
README.rst
pyproject.toml
whoseline/__init__.py
whoseline/app.py
whoseline/asplund_2021.txt
whoseline/cli.py
whoseline/version.py
whoseline.egg-info/PKG-INFO
whoseline.egg-info/SOURCES.txt
whoseline.egg-info/dependency_links.txt
whoseline.egg-info/entry_points.txt
whoseline.egg-info/requires.txt
whoseline.egg-info/top_level.txt