Metadata-Version: 2.2
Name: whoseline
Version: 0.0.2
Summary: Whose line is it anyway? An interactive tool for identifying atomic spectral lines.
License: MIT License
Project-URL: repository, https://github.com/bmorris3/whoseline
License-File: LICENSE
Requires-Dist: matplotlib
Requires-Dist: solara
Requires-Dist: ipywidgets
Requires-Dist: numpy
Requires-Dist: astropy
Requires-Dist: astroquery
Requires-Dist: expecto
Requires-Dist: specutils
Requires-Dist: pandas
